pmcm/__init__.py
pmcm/api.py
pmcm/main.py
pmcm/pmcm.py
pmcm/version.py
bmcs_fragmentation-0.0.2a0.dist-info/LICENSE
bmcs_fragmentation-0.0.2a0.dist-info/METADATA
bmcs_fragmentation-0.0.2a0.dist-info/WHEEL
bmcs_fragmentation-0.0.2a0.dist-info/top_level.txt
bmcs_fragmentation-0.0.2a0.dist-info/RECORD
