Metadata-Version: 2.1
Name: bmcs-fragmentation
Version: 0.0.2a0
Summary: Brittle-Matrix Composite Fragmentation.
Home-page: https://github.com/bmcs-group/bmcs_fragmentation
Author: BMCS-Group
Author-email: rostislav.chudoba@rwt-aachen.de
License: MIT
Platform: UNKNOWN
Classifier: License :: OSI Approved :: MIT License
Classifier: Programming Language :: Python
Classifier: Programming Language :: Python :: 3
Classifier: Programming Language :: Python :: 3.6
Classifier: Programming Language :: Python :: Implementation :: CPython
Classifier: Programming Language :: Python :: Implementation :: PyPy
Requires-Python: >=3.6.0
